vrp_solver_ignore/ParentSolver.py
vrp_solver_ignore/SolverClassic.py
vrp_solver_ignore/SolverIgnore.py
vrp_solver_ignore/SolverIgnoreMultiplicity.py
vrp_solver_ignore/SolverIncremental.py
vrp_solver_ignore/SolverKBest.py
vrp_solver_ignore/__init__.py
vrp_solver_ignore/cppWrapper.pyd
vrp_solver_ignore-0.1.1.dist-info/METADATA
vrp_solver_ignore-0.1.1.dist-info/WHEEL
vrp_solver_ignore-0.1.1.dist-info/top_level.txt
vrp_solver_ignore-0.1.1.dist-info/RECORD
